jupyterhub_carina/CarinaAuthenticator.py
jupyterhub_carina/CarinaOAuthClient.py
jupyterhub_carina/CarinaSpawner.py
jupyterhub_carina/__init__.py
jupyterhub_carina/_version.py
jupyterhub_carina-0.2.2.dist-info/DESCRIPTION.rst
jupyterhub_carina-0.2.2.dist-info/METADATA
jupyterhub_carina-0.2.2.dist-info/RECORD
jupyterhub_carina-0.2.2.dist-info/WHEEL
jupyterhub_carina-0.2.2.dist-info/metadata.json
jupyterhub_carina-0.2.2.dist-info/top_level.txt
