Metadata-Version: 2.0
Name: jupyterhub-carina
Version: 0.2.2
Summary: Carina support for JupyterHub
Home-page: https://jupyter.org
Author: Jupyter Development Team
Author-email: jupyter@googlegroups.com
License: BSD
Keywords: Interactive,Interpreter,Shell,Web,Carina
Platform: Linux
Platform: Mac OS X
Classifier: Intended Audience :: Developers
Classifier: Intended Audience :: System Administrators
Classifier: Intended Audience :: Science/Research
Classifier: License :: OSI Approved :: BSD License
Classifier: Programming Language :: Python
Classifier: Programming Language :: Python :: 3
Requires-Dist: dockerspawner (>=0.3.0)
Requires-Dist: jupyterhub (>=0.5.0)
Requires-Dist: oauthenticator (>=0.3.0)
